README.md
setup.py
m_kafka_sdk.egg-info/PKG-INFO
m_kafka_sdk.egg-info/SOURCES.txt
m_kafka_sdk.egg-info/dependency_links.txt
m_kafka_sdk.egg-info/requires.txt
m_kafka_sdk.egg-info/top_level.txt
mobio/libs/kafka_lib/__init__.py
mobio/libs/kafka_lib/helpers/__init__.py
mobio/libs/kafka_lib/helpers/confluent_producer_manager.py
mobio/libs/kafka_lib/helpers/confulent_consumer_manager.py
mobio/libs/kafka_lib/helpers/ensure_kafka_topic.py
mobio/libs/kafka_lib/models/__init__.py
mobio/libs/kafka_lib/models/mongo/__init__.py
mobio/libs/kafka_lib/models/mongo/base_model.py
mobio/libs/kafka_lib/models/mongo/requeue_consumer_model.py