Metadata-Version: 2.1
Name: m-kafka-sdk
Version: 0.1.6
Summary: Mobio Kafka SDK
Home-page: https://github.com/mobiovn
Author: MOBIO
Author-email: contact@mobio.vn
License: MIT
Classifier: Topic :: Software Development
Classifier: Development Status :: 4 - Beta
Classifier: Intended Audience :: Developers
Classifier: License :: OSI Approved :: MIT License
Classifier: Programming Language :: Python :: 3
Classifier: Programming Language :: Python :: 3.4
Classifier: Programming Language :: Python :: 3.5
Classifier: Programming Language :: Python :: 3.6
Classifier: Programming Language :: Python :: 3.7
Classifier: Programming Language :: Python :: Implementation :: CPython
Classifier: Programming Language :: Python :: Implementation :: PyPy
